pychurros/__init__.py
pychurros/base.py
pychurros/churros_repository.py
pychurros/dynamic_query_mixin.py
pychurros-0.1.1.dist-info/LICENSE
pychurros-0.1.1.dist-info/METADATA
pychurros-0.1.1.dist-info/WHEEL
pychurros-0.1.1.dist-info/top_level.txt
pychurros-0.1.1.dist-info/RECORD
