Metadata-Version: 2.2
Name: pychurros
Version: 0.1.1
Summary: A dynamic repository library for SQLModel in Python
Author: Gustavo Valle
Author-email: Gustavo Valle <gustavo@devcrafter.io>
License: Apache 2.0
Project-URL: Homepage, https://github.com/churros-py/churros-data-ppa
Project-URL: Documentation, https://github.com/churros-py/churros-data-ppa
Project-URL: Source, https://github.com/churros-py/churros-data-ppa
Requires-Python: >=3.9
License-File: LICENSE
Requires-Dist: sqlmodel
Requires-Dist: fastapi
